example.py
pymtml.py
mthreads_ml_py-2.2.10.dist-info/LICENSE
mthreads_ml_py-2.2.10.dist-info/METADATA
mthreads_ml_py-2.2.10.dist-info/WHEEL
mthreads_ml_py-2.2.10.dist-info/top_level.txt
mthreads_ml_py-2.2.10.dist-info/RECORD
