Metadata-Version: 2.1
Name: mthreads-ml-py
Version: 2.2.10
Summary: Python Bindings for the Moore Threads GPU Management Library
Home-page: https://developer.mthreads.com
Author: Moore Threads Corporation
Author-email: mt-sw-cloudcomputing@mthreads.com
License: MIT
Classifier: Development Status :: 5 - Production/Stable
Classifier: Intended Audience :: Developers
Classifier: Intended Audience :: System Administrators
Classifier: License :: OSI Approved :: MIT License
Classifier: Operating System :: Microsoft :: Windows
Classifier: Operating System :: POSIX :: Linux
Classifier: Programming Language :: Python
Classifier: Topic :: Software Development :: Libraries :: Python Modules
Classifier: Topic :: System :: Hardware
Classifier: Topic :: System :: Systems Administration
License-File: LICENSE
